README.md
setup.cfg
setup.py
kombu_producer/__init__.py
kombu_producer/kombu_producer.py
kombu_producer/utils.py
kombu_producer.egg-info/PKG-INFO
kombu_producer.egg-info/SOURCES.txt
kombu_producer.egg-info/dependency_links.txt
kombu_producer.egg-info/requires.txt
kombu_producer.egg-info/top_level.txt